README.md
setup.cfg
setup.py
bhalle_example/__init__.py
bhalle_example/api_client.py
bhalle_example/configuration.py
bhalle_example/exceptions.py
bhalle_example/rest.py
bhalle_example.egg-info/PKG-INFO
bhalle_example.egg-info/SOURCES.txt
bhalle_example.egg-info/dependency_links.txt
bhalle_example.egg-info/requires.txt
bhalle_example.egg-info/top_level.txt
bhalle_example/api/__init__.py
bhalle_example/api/pets_api.py
bhalle_example/models/__init__.py
bhalle_example/models/error.py
bhalle_example/models/pet.py
test/test_error.py
test/test_pet.py
test/test_pets_api.py