Metadata-Version: 1.0
Name: bhalle-example
Version: 1.3.30b1
Summary: Swagger Petstore
Home-page: https://github.com/bhalle/client-python
Author: OpenAPI Generator community
Author-email: team@openapitools.org
License: MIT
Keywords: OpenAPI,OpenAPI-Generator,Swagger Petstore
Platform: UNKNOWN
